RPDB/__init__.py
RPDB/database.py
RP_DataBase-1.1.1.dist-info/METADATA
RP_DataBase-1.1.1.dist-info/WHEEL
RP_DataBase-1.1.1.dist-info/top_level.txt
RP_DataBase-1.1.1.dist-info/RECORD
