Metadata-Version: 2.1
Name: RP-DataBase
Version: 1.1.1
Summary: a database
Home-page: https://github.com/hsn8086/RPDB
Author: hsn8086
Author-email: hsn1919810@gmail.com
License: MIT license
